Workbook

Sheet Допущения
A1: Допущения модели
A3: Инвестиции в запуск, ₽ | B3: 2400000
A4: Средний чек, ₽ | B4: 390
A5: Чеков в день на старте | B5: 70
A6: Чеков в день на плато | B6: 190
A7: Месяцев до плато | B7: 9
A8: Рабочих дней в месяце | B8: 30
A9: Себестоимость, % от выручки | B9: 0.31
A10: Аренда, ₽/мес | B10: 180000
A11: ФОТ, ₽/мес | B11: 420000
A12: Прочие постоянные, ₽/мес | B12: 90000
A13: Эквайринг и налог, % от выручки | B13: 0.085
A14: Маркетинг на старте, ₽/мес | B14: 120000
A15: Маркетинг после плато, ₽/мес | B15: 50000

Sheet P&L
A1: Месяц | B1: 1 | C1: 2 | D1: 3 | E1: 4 | F1: 5 | G1: 6 | H1: 7 | I1: 8 | J1: 9 | K1: 10 | L1: 11 | M1: 12 | N1: 13 | O1: 14 | P1: 15 | Q1: 16 | R1: 17 | S1: 18 | T1: 19 | U1: 20 | V1: 21 | W1: 22 | X1: 23 | Y1: 24
A2: Чеков в день | B2: =IF(1>=Допущения!$B$7,Допущения!$B$6,Допущения!$B$5+(Допущения!$B$6-Допущения!$B$5)*(1-1)/(Допущения!$B$7-1)) | C2: =IF(2>=Допущения!$B$7,Допущения!$B$6,Допущения!$B$5+(Допущения!$B$6-Допущения!$B$5)*(2-1)/(Допущения!$B$7-1)) | D2: =IF(3>=Допущения!$B$7,Допущения!$B$6,Допущения!$B$5+(Допущения!$B$6-Допущения!$B$5)*(3-1)/(Допущения!$B$7-1)) | E2: =IF(4>=Допущения!$B$7,Допущения!$B$6,Допущения!$B$5+(Допущения!$B$6-Допущения!$B$5)*(4-1)/(Допущения!$B$7-1)) | F2: =IF(5>=Допущения!$B$7,Допущения!$B$6,Допущения!$B$5+(Допущения!$B$6-Допущения!$B$5)*(5-1)/(Допущения!$B$7-1)) | G2: =IF(6>=Допущения!$B$7,Допущения!$B$6,Допущения!$B$5+(Допущения!$B$6-Допущения!$B$5)*(6-1)/(Допущения!$B$7-1)) | H2: =IF(7>=Допущения!$B$7,Допущения!$B$6,Допущения!$B$5+(Допущения!$B$6-Допущения!$B$5)*(7-1)/(Допущения!$B$7-1)) | I2: =IF(8>=Допущения!$B$7,Допущения!$B$6,Допущения!$B$5+(Допущения!$B$6-Допущения!$B$5)*(8-1)/(Допущения!$B$7-1)) | J2: =IF(9>=Допущения!$B$7,Допущения!$B$6,Допущения!$B$5+(Допущения!$B$6-Допущения!$B$5)*(9-1)/(Допущения!$B$7-1)) | K2: =IF(10>=Допущения!$B$7,Допущения!$B$6,Допущения!$B$5+(Допущения!$B$6-Допущения!$B$5)*(10-1)/(Допущения!$B$7-1)) | L2: =IF(11>=Допущения!$B$7,Допущения!$B$6,Допущения!$B$5+(Допущения!$B$6-Допущения!$B$5)*(11-1)/(Допущения!$B$7-1)) | M2: =IF(12>=Допущения!$B$7,Допущения!$B$6,Допущения!$B$5+(Допущения!$B$6-Допущения!$B$5)*(12-1)/(Допущения!$B$7-1)) | N2: =IF(13>=Допущения!$B$7,Допущения!$B$6,Допущения!$B$5+(Допущения!$B$6-Допущения!$B$5)*(13-1)/(Допущения!$B$7-1)) | O2: =IF(14>=Допущения!$B$7,Допущения!$B$6,Допущения!$B$5+(Допущения!$B$6-Допущения!$B$5)*(14-1)/(Допущения!$B$7-1)) | P2: =IF(15>=Допущения!$B$7,Допущения!$B$6,Допущения!$B$5+(Допущения!$B$6-Допущения!$B$5)*(15-1)/(Допущения!$B$7-1)) | Q2: =IF(16>=Допущения!$B$7,Допущения!$B$6,Допущения!$B$5+(Допущения!$B$6-Допущения!$B$5)*(16-1)/(Допущения!$B$7-1)) | R2: =IF(17>=Допущения!$B$7,Допущения!$B$6,Допущения!$B$5+(Допущения!$B$6-Допущения!$B$5)*(17-1)/(Допущения!$B$7-1)) | S2: =IF(18>=Допущения!$B$7,Допущения!$B$6,Допущения!$B$5+(Допущения!$B$6-Допущения!$B$5)*(18-1)/(Допущения!$B$7-1)) | T2: =IF(19>=Допущения!$B$7,Допущения!$B$6,Допущения!$B$5+(Допущения!$B$6-Допущения!$B$5)*(19-1)/(Допущения!$B$7-1)) | U2: =IF(20>=Допущения!$B$7,Допущения!$B$6,Допущения!$B$5+(Допущения!$B$6-Допущения!$B$5)*(20-1)/(Допущения!$B$7-1)) | V2: =IF(21>=Допущения!$B$7,Допущения!$B$6,Допущения!$B$5+(Допущения!$B$6-Допущения!$B$5)*(21-1)/(Допущения!$B$7-1)) | W2: =IF(22>=Допущения!$B$7,Допущения!$B$6,Допущения!$B$5+(Допущения!$B$6-Допущения!$B$5)*(22-1)/(Допущения!$B$7-1)) | X2: =IF(23>=Допущения!$B$7,Допущения!$B$6,Допущения!$B$5+(Допущения!$B$6-Допущения!$B$5)*(23-1)/(Допущения!$B$7-1)) | Y2: =IF(24>=Допущения!$B$7,Допущения!$B$6,Допущения!$B$5+(Допущения!$B$6-Допущения!$B$5)*(24-1)/(Допущения!$B$7-1))
A3: Выручка | B3: =B2*B14*Допущения!$B$4*Допущения!$B$8 | C3: =C2*C14*Допущения!$B$4*Допущения!$B$8 | D3: =D2*D14*Допущения!$B$4*Допущения!$B$8 | E3: =E2*E14*Допущения!$B$4*Допущения!$B$8 | F3: =F2*F14*Допущения!$B$4*Допущения!$B$8 | G3: =G2*G14*Допущения!$B$4*Допущения!$B$8 | H3: =H2*H14*Допущения!$B$4*Допущения!$B$8 | I3: =I2*I14*Допущения!$B$4*Допущения!$B$8 | ... Y3: =Y2*Y14*Допущения!$B$4*Допущения!$B$8
A4: Себестоимость | B4: =-B3*Допущения!$B$9 | C4: =-C3*Допущения!$B$9 | D4: =-D3*Допущения!$B$9 | E4: =-E3*Допущения!$B$9 | F4: =-F3*Допущения!$B$9 | G4: =-G3*Допущения!$B$9 | H4: =-H3*Допущения!$B$9 | I4: =-I3*Допущения!$B$9 | ... Y4: =-Y3*Допущения!$B$9
A5: Валовая прибыль | B5: =B3+B4 | C5: =C3+C4 | D5: =D3+D4 | E5: =E3+E4 | F5: =F3+F4 | G5: =G3+G4 | H5: =H3+H4 | I5: =I3+I4 | ... Y5: =Y3+Y4
A6: Аренда | B6: =-Допущения!$B$10 | C6: =-Допущения!$B$10 | D6: =-Допущения!$B$10 | E6: =-Допущения!$B$10 | F6: =-Допущения!$B$10 | G6: =-Допущения!$B$10 | H6: =-Допущения!$B$10 | I6: =-Допущения!$B$10 | ... Y6: =-Допущения!$B$10
A7: ФОТ | B7: =-Допущения!$B$11 | C7: =-Допущения!$B$11 | D7: =-Допущения!$B$11 | E7: =-Допущения!$B$11 | F7: =-Допущения!$B$11 | G7: =-Допущения!$B$11 | H7: =-Допущения!$B$11 | I7: =-Допущения!$B$11 | ... Y7: =-Допущения!$B$11
A8: Маркетинг | B8: =-IF(1>=Допущения!$B$7,Допущения!$B$15,Допущения!$B$14) | C8: =-IF(2>=Допущения!$B$7,Допущения!$B$15,Допущения!$B$14) | D8: =-IF(3>=Допущения!$B$7,Допущения!$B$15,Допущения!$B$14) | E8: =-IF(4>=Допущения!$B$7,Допущения!$B$15,Допущения!$B$14) | F8: =-IF(5>=Допущения!$B$7,Допущения!$B$15,Допущения!$B$14) | G8: =-IF(6>=Допущения!$B$7,Допущения!$B$15,Допущения!$B$14) | H8: =-IF(7>=Допущения!$B$7,Допущения!$B$15,Допущения!$B$14) | I8: =-IF(8>=Допущения!$B$7,Допущения!$B$15,Допущения!$B$14) | J8: =-IF(9>=Допущения!$B$7,Допущения!$B$15,Допущения!$B$14) | K8: =-IF(10>=Допущения!$B$7,Допущения!$B$15,Допущения!$B$14) | L8: =-IF(11>=Допущения!$B$7,Допущения!$B$15,Допущения!$B$14) | M8: =-IF(12>=Допущения!$B$7,Допущения!$B$15,Допущения!$B$14) | N8: =-IF(13>=Допущения!$B$7,Допущения!$B$15,Допущения!$B$14) | O8: =-IF(14>=Допущения!$B$7,Допущения!$B$15,Допущения!$B$14) | P8: =-IF(15>=Допущения!$B$7,Допущения!$B$15,Допущения!$B$14) | Q8: =-IF(16>=Допущения!$B$7,Допущения!$B$15,Допущения!$B$14) | R8: =-IF(17>=Допущения!$B$7,Допущения!$B$15,Допущения!$B$14) | S8: =-IF(18>=Допущения!$B$7,Допущения!$B$15,Допущения!$B$14) | T8: =-IF(19>=Допущения!$B$7,Допущения!$B$15,Допущения!$B$14) | U8: =-IF(20>=Допущения!$B$7,Допущения!$B$15,Допущения!$B$14) | V8: =-IF(21>=Допущения!$B$7,Допущения!$B$15,Допущения!$B$14) | W8: =-IF(22>=Допущения!$B$7,Допущения!$B$15,Допущения!$B$14) | X8: =-IF(23>=Допущения!$B$7,Допущения!$B$15,Допущения!$B$14) | Y8: =-IF(24>=Допущения!$B$7,Допущения!$B$15,Допущения!$B$14)
A9: Прочие постоянные | B9: =-Допущения!$B$12 | C9: =-Допущения!$B$12 | D9: =-Допущения!$B$12 | E9: =-Допущения!$B$12 | F9: =-Допущения!$B$12 | G9: =-Допущения!$B$12 | H9: =-Допущения!$B$12 | I9: =-Допущения!$B$12 | ... Y9: =-Допущения!$B$12
A10: Эквайринг и налог | B10: =-B3*Допущения!$B$13 | C10: =-C3*Допущения!$B$13 | D10: =-D3*Допущения!$B$13 | E10: =-E3*Допущения!$B$13 | F10: =-F3*Допущения!$B$13 | G10: =-G3*Допущения!$B$13 | H10: =-H3*Допущения!$B$13 | I10: =-I3*Допущения!$B$13 | ... Y10: =-Y3*Допущения!$B$13
A11: Операционная прибыль | B11: =SUM(B5:B10) | C11: =SUM(C5:C10) | D11: =SUM(D5:D10) | E11: =SUM(E5:E10) | F11: =SUM(F5:F10) | G11: =SUM(G5:G10) | H11: =SUM(H5:H10) | I11: =SUM(I5:I10) | ... Y11: =SUM(Y5:Y10)
A12: Денежный поток накопленный | B12: =-Допущения!$B$3+B11 | C12: =B12+C11 | D12: =C12+D11 | E12: =D12+E11 | F12: =E12+F11 | G12: =F12+G11 | H12: =G12+H11 | I12: =H12+I11 | J12: =I12+J11 | ... Y12: =X12+Y11
A14: Сезонный коэффициент | B14: 0.86 | C14: 0.9 | D14: 0.97 | E14: 1.02 | F14: 1.08 | G14: 1.12 | H14: 1.14 | I14: 1.1 | J14: 1.04 | K14: 0.98 | L14: 0.93 | M14: 1.02 | N14: 0.86 | O14: 0.9 | P14: 0.97 | Q14: 1.02 | R14: 1.08 | S14: 1.12 | T14: 1.14 | U14: 1.1 | V14: 1.04 | W14: 0.98 | X14: 0.93 | Y14: 1.02

Sheet Итоги
A1: Ключевые показатели
A3: Выручка за 2 года, ₽ | B3: =SUM('P&L'!B3:Y3)
A4: Операционная прибыль за 2 года, ₽ | B4: =SUM('P&L'!B11:Y11)
A5: Первый прибыльный месяц | B5: =IFERROR(MATCH(TRUE,INDEX('P&L'!B11:Y11>0,0),0),"нет")
A6: Месяц окупаемости | B6: =IFERROR(MATCH(TRUE,INDEX('P&L'!B12:Y12>=0,0),0),"> 24")
A7: Точка безубыточности, чеков в день | B7: =(Допущения!$B$10+Допущения!$B$11+Допущения!$B$12+Допущения!$B$15)/(Допущения!$B$4*Допущения!$B$8*(1-Допущения!$B$9-Допущения!$B$13))
